openxlab/__init__.py
openxlab/cli.py
openxlab/config/__init__.py
openxlab/config/const.py
openxlab/config/version.py
openxlab/dataset/__init__.py
openxlab/dataset/constants.py
openxlab/dataset/exception.py
openxlab/dataset/utils.py
openxlab/dataset/client/__init__.py
openxlab/dataset/client/api.py
openxlab/dataset/client/client.py
openxlab/dataset/client/uaa.py
openxlab/dataset/commands/__init__.py
openxlab/dataset/commands/commit.py
openxlab/dataset/commands/create.py
openxlab/dataset/commands/download.py
openxlab/dataset/commands/get.py
openxlab/dataset/commands/info.py
openxlab/dataset/commands/ls.py
openxlab/dataset/commands/remove.py
openxlab/dataset/commands/upload_file.py
openxlab/dataset/commands/upload_folder.py
openxlab/dataset/commands/utility.py
openxlab/dataset/commands/visibility.py
openxlab/dataset/handler/__init__.py
openxlab/dataset/handler/commit_dataset_info.py
openxlab/dataset/handler/create_dataset_repository.py
openxlab/dataset/handler/download_dataset_repository.py
openxlab/dataset/handler/get_dataset_repository.py
openxlab/dataset/handler/info_dataset_repository.py
openxlab/dataset/handler/list_dataset_repository.py
openxlab/dataset/handler/remove_dataset_repository.py
openxlab/dataset/handler/upload_dataset_file.py
openxlab/dataset/handler/upload_dataset_folder.py
openxlab/dataset/handler/visible_dataset_repository.py
openxlab/dataset/io/__init__.py
openxlab/dataset/io/downloader.py
openxlab/dataset/io/upload.py
openxlab/dataset/utility/__init__.py
openxlab/dataset/utility/concurrency.py
openxlab/demo_cmd/__init__.py
openxlab/model/__init__.py
openxlab/model/clients/__init__.py
openxlab/model/clients/model_client.py
openxlab/model/clients/modelapi_client.py
openxlab/model/clients/openapi_client.py
openxlab/model/clients/oss_client.py
openxlab/model/clients/upload_service_client.py
openxlab/model/commands/__init__.py
openxlab/model/commands/create.py
openxlab/model/commands/download.py
openxlab/model/commands/inference.py
openxlab-0.1.1.dist-info/METADATA
openxlab-0.1.1.dist-info/WHEEL
openxlab-0.1.1.dist-info/entry_points.txt
openxlab-0.1.1.dist-info/RECORD
